pep440check/__init__.py
pep440check/main.py
pep440check/pep440check.py
pep440check-0.0.2.dist-info/WHEEL
pep440check-0.0.2.dist-info/entry_points.txt
pep440check-0.0.2.dist-info/METADATA
pep440check-0.0.2.dist-info/RECORD
