Metadata-Version: 2.3
Name: pep440check
Version: 0.0.2
Summary: Check and normalize PEP 440 version strings in pyproject.toml
Keywords: pep440,python,version,pyproject,packaging,tool
Author: heiwa4126
Author-email: heiwa4126 <heiwa4126@gmail.com>
License: MIT License
Classifier: License :: OSI Approved :: MIT License
Classifier: Operating System :: OS Independent
Classifier: Programming Language :: Python :: 3
Requires-Dist: packaging
Requires-Python: >=3.9
Project-URL: Documentation, https://github.com/heiwa4126/pep440check#readme
Project-URL: Issues, https://github.com/heiwa4126/pep440check/issues
Project-URL: Source, https://github.com/heiwa4126/pep440check
